pudzu/pillar/__init__.py
pudzu/pillar/pillar.py
pudzu_pillar-0.9.3.dist-info/METADATA
pudzu_pillar-0.9.3.dist-info/WHEEL
pudzu_pillar-0.9.3.dist-info/RECORD
