Metadata-Version: 2.1
Name: pudzu-pillar
Version: 0.9.3
Summary: Various imaging utilities, monkey-patched onto Pillow
Home-page: https://github.com/Udzu/pudzu-packages/pudzu-pillar/
License: MIT
Keywords: pudzu,imaging,pillow
Author: Uri Granta
Author-email: uri.granta+python@gmail.com
Requires-Python: >=3.7,<4.0
Classifier: License :: OSI Approved :: MIT License
Classifier: Operating System :: OS Independent
Classifier: Programming Language :: Python :: 3
Classifier: Programming Language :: Python :: 3.7
Classifier: Programming Language :: Python :: 3.8
Classifier: Programming Language :: Python :: 3.9
Classifier: Programming Language :: Python :: 3.10
Classifier: Programming Language :: Python :: 3.11
Classifier: Programming Language :: Python :: 3.12
Provides-Extra: image-extras
Provides-Extra: text-extras
Requires-Dist: Pillow (>=6.0.0,<10.0.0)
Requires-Dist: arabic-reshaper (>=2.0.15,<3.0.0) ; extra == "text-extras"
Requires-Dist: numpy (>=1.16.0,<2.0.0)
Requires-Dist: pudzu-utils (>=0.9.3,<0.10.0)
Requires-Dist: pyphen (>=0.10.0,<0.11.0) ; extra == "text-extras"
Requires-Dist: python-bidi (>=0.4.2,<0.5.0) ; extra == "text-extras"
Requires-Dist: requests (>=2.22.0,<3.0.0) ; extra == "image-extras"
Requires-Dist: scipy (>=1.3.1,<2.0.0) ; extra == "image-extras"
